pyw/__init__.py
pyw/musicparser/__init__.py
pyw_musicparser-0.0.0.post2.dist-info/METADATA
pyw_musicparser-0.0.0.post2.dist-info/WHEEL
pyw_musicparser-0.0.0.post2.dist-info/licenses/LICENSE
pyw_musicparser-0.0.0.post2.dist-info/RECORD
