Metadata-Version: 2.4
Name: pyw-musicparser
Version: 0.0.0.post2
Summary: Parse MIDI/Lilypond into music21 (placeholder)
Project-URL: Homepage, https://github.com/pythonWoods/pyw-musicparser
Project-URL: Documentation, https://pythonwoods.dev/docs/pyw-musicparser/latest/
Project-URL: Issues, https://github.com/pythonWoods/pyw-musicparser/issues
Project-URL: Changelog, https://github.com/pythonWoods/pyw-musicparser/releases
Author: pythonWoods
License: MIT
License-File: LICENSE
Classifier: Development Status :: 2 - Pre-Alpha
Classifier: License :: OSI Approved :: MIT License
Classifier: Programming Language :: Python :: 3 :: Only
Classifier: Programming Language :: Python :: 3.11
Classifier: Typing :: Typed
Requires-Python: >=3.9
Requires-Dist: music21>=9
Requires-Dist: pretty-midi>=0.2
Requires-Dist: pyw-core>=0.0.0
